Metadata-Version: 2.4
Name: tavily_server_mcp
Version: 0.2.0
Summary: A custom MCP server implementation
Author-email: Your Name <your.email@example.com>
License-File: LICENSE
Classifier: License :: OSI Approved :: MIT License
Classifier: Operating System :: OS Independent
Classifier: Programming Language :: Python :: 3
Requires-Python: >=3.8
Requires-Dist: fastapi>=0.100.0
Requires-Dist: fastmcp>=2.11.0
Requires-Dist: httpx>=0.24.0
Requires-Dist: pydantic>=2.0.0
Requires-Dist: python-dotenv>=1.0.0
Requires-Dist: tavily-python>=0.3.0
Requires-Dist: uvicorn>=0.24.0
Provides-Extra: dev
Requires-Dist: black; extra == 'dev'
Requires-Dist: build; extra == 'dev'
Requires-Dist: isort; extra == 'dev'
Requires-Dist: mypy; extra == 'dev'
Requires-Dist: pytest; extra == 'dev'
Requires-Dist: pytest-cov; extra == 'dev'
Requires-Dist: twine; extra == 'dev'
